trading212/__init__.py
trading212/client.py
trading212_api_py-0.1.9.dist-info/licenses/LICENCE
trading212_api_py-0.1.9.dist-info/METADATA
trading212_api_py-0.1.9.dist-info/WHEEL
trading212_api_py-0.1.9.dist-info/top_level.txt
trading212_api_py-0.1.9.dist-info/RECORD
