Metadata-Version: 2.4
Name: trading212-api-py
Version: 0.1.9
Summary: A Python client for the Trading212 API.
Author-email: Angus Clinch <angus.clinch@gmail.com>
License-Expression: GPL-3.0-or-later
Project-URL: Homepage, https://github.com/clincha/trading212-api-py
Project-URL: Issues, https://github.com/clincha/trading212-api-py/issues
Classifier: Programming Language :: Python :: 3
Classifier: Operating System :: OS Independent
Requires-Python: >=3.9
License-File: LICENCE
Dynamic: license-file
